day12/counter_4.v
module counter_4 (input clk, direc, rst, output [3:0] counter);

reg [3:0] count = 0 ;

assign counter = count;

always @ (rst, direc, clk)
	
begin
	if (rst)
		begin
		count = 4'b0;
		end
	else if (direc == 1)
		begin
		count = count + 1;
		if (count == 4'b1111)
		count = 0;
		end
	else if (direc == 0)
		begin
		count = count - 1;
		if (count == 0)
		count = 4'b1111;
		end
end

endmodule

day12/counter_4_tb.v
module counter_4_tb ();
reg clk = 0, direc, rst;
wire [3:0] counter;

counter_4 DUT (clk, direc, rst, counter);

always #5 clk = ~clk;

initial
begin
	rst = 1;
#20	rst = 0 ;direc = 1;
#200	direc = 0;

end

initial 
begin
	$dumpfile("counter_4_tb.vcd");
	$dumpvars;
	#400 $finish;
end

endmodule

day12/counter_4_tb.vcd
$date
	Wed Sep 20 12:37:49 2023
$end
$version
	Icarus Verilog
$end
$timescale
	1s
$end
$scope module counter_4_tb $end
$var wire 4 ! counter [3:0] $end
$var reg 1 " clk $end
$var reg 1 # direc $end
$var reg 1 $ rst $end
$scope module DUT $end
$var wire 1 " clk $end
$var wire 4 % counter [3:0] $end
$var wire 1 # direc $end
$var wire 1 $ rst $end
$var reg 4 & count [3:0] $end
$upscope $end
$upscope $end
$enddefinitions $end
#0
$dumpvars
b0 &
b0 %
1$
x#
0"
b0 !
$end
#5
1"
#10
0"
#15
1"
#20
b1 !
b1 %
b1 &
0"
1#
0$
#25
b10 !
b10 %
b10 &
1"
#30
b11 !
b11 %
b11 &
0"
#35
b100 !
b100 %
b100 &
1"
#40
b101 !
b101 %
b101 &
0"
#45
b110 !
b110 %
b110 &
1"
#50
b111 !
b111 %
b111 &
0"
#55
b1000 !
b1000 %
b1000 &
1"
#60
b1001 !
b1001 %
b1001 &
0"
#65
b1010 !
b1010 %
b1010 &
1"
#70
b1011 !
b1011 %
b1011 &
0"
#75
b1100 !
b1100 %
b1100 &
1"
#80
b1101 !
b1101 %
b1101 &
0"
#85
b1110 !
b1110 %
b1110 &
1"
#90
b0 !
b0 %
b0 &
0"
#95
b1 !
b1 %
b1 &
1"
#100
b10 !
b10 %
b10 &
0"
#105
b11 !
b11 %
b11 &
1"
#110
b100 !
b100 %
b100 &
0"
#115
b101 !
b101 %
b101 &
1"
#120
b110 !
b110 %
b110 &
0"
#125
b111 !
b111 %
b111 &
1"
#130
b1000 !
b1000 %
b1000 &
0"
#135
b1001 !
b1001 %
b1001 &
1"
#140
b1010 !
b1010 %
b1010 &
0"
#145
b1011 !
b1011 %
b1011 &
1"
#150
b1100 !
b1100 %
b1100 &
0"
#155
b1101 !
b1101 %
b1101 &
1"
#160
b1110 !
b1110 %
b1110 &
0"
#165
b0 !
b0 %
b0 &
1"
#170
b1 !
b1 %
b1 &
0"
#175
b10 !
b10 %
b10 &
1"
#180
b11 !
b11 %
b11 &
0"
#185
b100 !
b100 %
b100 &
1"
#190
b101 !
b101 %
b101 &
0"
#195
b110 !
b110 %
b110 &
1"
#200
b111 !
b111 %
b111 &
0"
#205
b1000 !
b1000 %
b1000 &
1"
#210
b1001 !
b1001 %
b1001 &
0"
#215
b1010 !
b1010 %
b1010 &
1"
#220
b1001 !
b1001 %
b1001 &
0"
0#
#225
b1000 !
b1000 %
b1000 &
1"
#230
b111 !
b111 %
b111 &
0"
#235
b110 !
b110 %
b110 &
1"
#240
b101 !
b101 %
b101 &
0"
#245
b100 !
b100 %
b100 &
1"
#250
b11 !
b11 %
b11 &
0"
#255
b10 !
b10 %
b10 &
1"
#260
b1 !
b1 %
b1 &
0"
#265
b1111 !
b1111 %
b1111 &
1"
#270
b1110 !
b1110 %
b1110 &
0"
#275
b1101 !
b1101 %
b1101 &
1"
#280
b1100 !
b1100 %
b1100 &
0"
#285
b1011 !
b1011 %
b1011 &
1"
#290
b1010 !
b1010 %
b1010 &
0"
#295
b1001 !
b1001 %
b1001 &
1"
#300
b1000 !
b1000 %
b1000 &
0"
#305
b111 !
b111 %
b111 &
1"
#310
b110 !
b110 %
b110 &
0"
#315
b101 !
b101 %
b101 &
1"
#320
b100 !
b100 %
b100 &
0"
#325
b11 !
b11 %
b11 &
1"
#330
b10 !
b10 %
b10 &
0"
#335
b1 !
b1 %
b1 &
1"
#340
b1111 !
b1111 %
b1111 &
0"
#345
b1110 !
b1110 %
b1110 &
1"
#350
b1101 !
b1101 %
b1101 &
0"
#355
b1100 !
b1100 %
b1100 &
1"
#360
b1011 !
b1011 %
b1011 &
0"
#365
b1010 !
b1010 %
b1010 &
1"
#370
b1001 !
b1001 %
b1001 &
0"
#375
b1000 !
b1000 %
b1000 &
1"
#380
b111 !
b111 %
b111 &
0"
#385
b110 !
b110 %
b110 &
1"
#390
b101 !
b101 %
b101 &
0"
#395
b100 !
b100 %
b100 &
1"
#400
b11 !
b11 %
b11 &
0"
